microstates.py
mne_microstates.py
mne_microstates-0.3.dist-info/LICENSE
mne_microstates-0.3.dist-info/METADATA
mne_microstates-0.3.dist-info/WHEEL
mne_microstates-0.3.dist-info/top_level.txt
mne_microstates-0.3.dist-info/RECORD
