Metadata-Version: 2.1
Name: mne-microstates
Version: 0.3
Summary: Code for microstate analysis, in combination with MNE-Python.
Home-page: https://github.com/wmvanvliet/mne_microstates
Maintainer: Marijn van Vliet
Maintainer-email: w.m.vanvliet@gmail.com
License: BSD-3
Platform: any
Classifier: Intended Audience :: Science/Research
Classifier: Intended Audience :: Developers
Classifier: License :: OSI Approved
Classifier: Programming Language :: Python
Classifier: Topic :: Software Development
Classifier: Topic :: Scientific/Engineering
Classifier: Operating System :: Microsoft :: Windows
Classifier: Operating System :: POSIX
Classifier: Operating System :: Unix
Classifier: Operating System :: MacOS
License-File: LICENSE
Requires-Dist: numpy
Requires-Dist: scipy
Requires-Dist: mne
